MANIFEST.in
setup.py
smysql/__init__.py
smysql/simple_mysql.py
smysql.egg-info/PKG-INFO
smysql.egg-info/SOURCES.txt
smysql.egg-info/dependency_links.txt
smysql.egg-info/not-zip-safe
smysql.egg-info/requires.txt
smysql.egg-info/top_level.txt