Metadata-Version: 1.1
Name: smysql
Version: 0.2.9
Summary: simple mysql orm
Home-page: https://github.com/ls0f/smysql
Author: ls0f
Author-email: ls0f@example.com
License: BSD
Platform: UNKNOWN
Classifier: License :: OSI Approved :: MIT License
Classifier: Programming Language :: Python
Classifier: Intended Audience :: Developers
Classifier: Operating System :: OS Independent
